[
  {
    "version": 677386,
    "release_date": "2025-07-03",
    "is_release": true,
    "is_hotfix": false,
    "is_pinned": false
  },
  {
    "version": 677072,
    "release_date": "2025-06-27",
    "is_release": true,
    "is_hotfix": true,
    "is_pinned": false
  },
  {
    "version": 676724,
    "release_date": "2025-06-26",
    "is_release": false,
    "is_hotfix": true,
    "is_pinned": false
  },
  {
    "version": 676312,
    "release_date": "2025-06-24",
    "is_release": true,
    "is_hotfix": true,
    "is_pinned": false
  },
  {
    "version": 676042,
    "release_date": "2025-06-20",
    "is_release": true,
    "is_hotfix": true,
    "is_pinned": false
  },
  {
    "version": 675849,
    "release_date": "2025-06-19",
    "is_release": true,
    "is_hotfix": true,
    "is_pinned": false
  },
  {
    "version": 675312,
    "release_date": "2025-06-16",
    "is_release": true,
    "is_hotfix": true,
    "is_pinned": false
  },
  {
    "version": 674842,
    "release_date": "2025-06-12",
    "is_release": true,
    "is_hotfix": true,
    "is_pinned": false
  },
  {
    "version": 674616,
    "release_date": "2025-06-12",
    "is_release": true,
    "is_hotfix": false,
    "is_pinned": true
  },
  {
    "version": 674594,
    "release_date": "2025-06-11",
    "is_release": false,
    "is_hotfix": true,
    "is_pinned": false
  },
  {
    "version": 674312,
    "release_date": "2025-06-10",
    "is_release": false,
    "is_hotfix": true,
    "is_pinned": false
  },
  {
    "version": 673753,
    "release_date": "2025-06-07",
    "is_release": false,
    "is_hotfix": true,
    "is_pinned": false
  },
  {
    "version": 673726,
    "release_date": "2025-06-06",
    "is_release": false,
    "is_hotfix": true,
    "is_pinned": false
  },
  {
    "version": 673461,
    "release_date": "2025-06-05",
    "is_release": false,
    "is_hotfix": true,
    "is_pinned": false
  },
  {
    "version": 671016,
    "release_date": "2025-05-23",
    "is_release": false,
    "is_hotfix": true,
    "is_pinned": false
  },
  {
    "version": 670859,
    "release_date": "2025-05-22",
    "is_release": false,
    "is_hotfix": true,
    "is_pinned": false
  },
  {
    "version": 670774,
    "release_date": "2025-05-22",
    "is_release": false,
    "is_hotfix": false,
    "is_pinned": false
  },
  {
    "version": 664453,
    "release_date": "2025-04-14",
    "is_release": true,
    "is_hotfix": true,
    "is_pinned": false
  },
  {
    "version": 664111,
    "release_date": "2025-04-10",
    "is_release": true,
    "is_hotfix": true,
    "is_pinned": false
  },
  {
    "version": 663947,
    "release_date": "2025-04-10",
    "is_release": true,
    "is_hotfix": false,
    "is_pinned": false
  },
  {
    "version": 662447,
    "release_date": "2025-04-01",
    "is_release": true,
    "is_hotfix": true,
    "is_pinned": false
  },
  {
    "version": 660872,
    "release_date": "2025-03-18",
    "is_release": true,
    "is_hotfix": true,
    "is_pinned": false
  },
  {
    "version": 658642,
    "release_date": "2025-03-05",
    "is_release": true,
    "is_hotfix": true,
    "is_pinned": false
  },
  {
    "version": 658406,
    "release_date": "2025-03-04",
    "is_release": true,
    "is_hotfix": true,
    "is_pinned": false
  },
  {
    "version": 657420,
    "release_date": "2025-02-27",
    "is_release": true,
    "is_hotfix": true,
    "is_pinned": false
  }
]